Workbook

Sheet IB - Civilitá
A1: IB — INDICADOR BASE | CIVILITÁ
A2: Conta 485827814343326 · BM 810267537957924 · BRL · America/Sao_Paulo
A3: Taxas reais medidas no período 08/07/2026 a 08/08/2026 (32 dias · R$3.722,83 · 109 compras)
A5: PARÂMETRO DE ENTRADA
A6: CPA ideal (meta de custo por venda) | B6: 43.85 | C6: ◄ altere aqui. Ver aba 'Cenários de CPA' para as opções justificadas.
A8: ETAPA DO FUNIL | B8: TAXA DE CONVERSÃO | C8: QTD POR VENDA | D8: CUSTO MÁXIMO
A9: Venda (Purchase) | B9: — | C9: 1 | D9: =$B$6 -> 43.85 | E9: medido no período: 109 compras
A10: Initiate Checkout × Purchase | B10: NÃO RASTREADO | C10: =C9 -> 1 | D10: =$B$6/C10 -> 43.85 | E10: evento inexistente no pixel — etapa colapsada (equivale a 100%)
A11: Add to Cart × Initiate Checkout | B11: 0.121246 | C11: =C10/B11 -> 8.2477064 | D11: =$B$6/C11 -> 5.3166296 | E11: medido: 109 ÷ 899 = 12,12% (na prática é ATC → Purchase)
A12: View Product × Add to Cart | B12: NÃO RASTREADO | C12: =C11 -> 8.2477064 | D12: =$B$6/C12 -> 5.3166296 | E12: evento ViewContent inexistente no pixel — etapa colapsada
A13: Page View × View Product | B13: 1.175163 | C13: =C12/B13 -> 7.0183486 | D13: =$B$6/C13 -> 6.2479085 | E13: medido: 899 ÷ 765 = 117,52% ⚠ IMPOSSÍVEL — ver aba 'Gaps de Tracking'
A15: CONNECT RATE | B15: CPC IDEAL | C15: CLIQUES POR VENDA | D15: CPC REAL MEDIDO
A16: 0.369208 | B16: =$B$6/C16 -> 2.3067809 | C16: =C13/A16 -> 19.009174 | D16: =Dados!B22 -> 1.7967326 | E16: medido: 765 LPV ÷ 2.072 cliques = 36,92%
A18: VEREDITO
A19: =IF(D16<=B16,"✅ FOLGA: o CPC real de "&TEXT(D16,"R$ 0.00")&" está ABAIXO do CPC ideal de "&TEXT(B16,"R$ 0.00")&". Sobra "&TEXT(B16-D16,"R$ 0.00")&" por clique.","🔴 ESTOURO: o CPC real de "&TEXT(D16,"R$ 0.00")&" excede o CPC ideal de "&TEXT(B16,"R$ 0.00")&".") -> ✅ FOLGA: o CPC real de R$ 1.80 está ABAIXO do CPC ideal de R$ 2.31. Sobra R$ 0.51 por clique.
A20: ="Para um CPA de "&TEXT(B6,"R$ 0.00")&" são necessários "&TEXT(C16,"0.0")&" cliques por venda. O real medido foi "&TEXT(Dados!B33,"0.0")&"." -> Para um CPA de R$ 43.85 são necessários 19.0 cliques por venda. O real medido foi 19.0.
A22: LEGENDA
A23: Amarelo | B23: preencher / alterar
A24: Verde | B24: resultado calculado
A25: Vermelho | B25: dado com defeito confirmado
A26: Cinza | B26: referência medida, não editar

Sheet Dados
A1: DADOS EXTRAÍDOS DA CONTA
A2: Fonte: Meta Ads API · nível conta · 08/07/2026 a 08/08/2026 · leitura READ-ONLY
A4: MÉTRICA | B4: VALOR | C4: ORIGEM
A5: Amount Spent | B5: 3722.83 | C5: Meta — direto
A6: Impressions | B6: 292642 | C6: Meta — direto
A7: Reach | B7: 43882 | C7: Meta — direto
A8: Frequency | B8: 6.668839 | C8: Meta — direto
A9: CPM | B9: 12.72 | C9: Meta — direto
A10: Link Clicks | B10: 2072 | C10: Meta — direto
A11: Outbound Clicks | B11: 1679 | C11: Meta — direto
A12: Landing Page Views | B12: 765 | C12: Meta — direto
A13: Add to Cart | B13: 899 | C13: Meta — direto
A14: Initiate Checkout | B14: — | C14: NÃO RASTREADO
A15: View Content | B15: — | C15: NÃO RASTREADO
A16: Purchases | B16: 109 | C16: Meta — direto
A17: Purchase Conversion Value | B17: 22582.77 | C17: Meta — direto (superestima 15%)
A19: DERIVADOS (fórmula)
A20: MÉTRICA | B20: VALOR | C20: CÁLCULO
A21: CTR (link) | B21: =B10/B6 -> 0.0070803234 | C21: Link Clicks ÷ Impressions
A22: CPC (link) | B22: =B5/B10 -> 1.7967326 | C22: Spend ÷ Link Clicks
A23: Custo por LPV | B23: =B5/B12 -> 4.8664444 | C23: Spend ÷ LPV
A24: Custo por ATC | B24: =B5/B13 -> 4.141079 | C24: Spend ÷ ATC
A25: CPA (atribuído) | B25: =B5/B16 -> 34.154404 | C25: Spend ÷ Purchases
A26: ROAS (plataforma) | B26: =B17/B5 -> 6.0660224 | C26: Valor ÷ Spend
A27: AOV (Meta) | B27: =B17/B16 -> 207.18138 | C27: Valor ÷ Purchases
A28: AOV (informado pelo negócio) | B28: 180 | C28: cliente — 21/08/2026
A29: Connect Rate | B29: =B12/B10 -> 0.36920849 | C29: LPV ÷ Link Clicks
A30: LPV → ATC | B30: =B13/B12 -> 1.1751634 | C30: ATC ÷ LPV ⚠ >100%
A31: ATC → Purchase | B31: =B16/B13 -> 0.12124583 | C31: Purchases ÷ ATC
A32: Clique → Purchase | B32: =B16/B10 -> 0.052606178 | C32: Purchases ÷ Link Clicks
A33: Cliques por venda | B33: =B10/B16 -> 19.009174 | C33: Link Clicks ÷ Purchases

Sheet Cenários de CPA
A1: CENÁRIOS DE CPA — qual meta usar no Indicador Base
A2: O CPA atribuído pela Meta e o CPA incremental real diferem por um fator de 2,44×. Planejar pelo atribuído sozinho superestima a entrega.
A4: CENÁRIO | B4: CPA ATRIBUÍDO | C4: CPA INCREMENTAL EQUIV. | D4: LTV/CAC @margem 20% | E4: AVALIAÇÃO
A5: A · CAC declarado pelo cliente | B5: 26 | C5: =B5*2.4374 -> 63.3724 | D5: =1600*0.2/C5 -> 5.0495168 | E5: muito conservador — LTV/CAC de 61× no CAC nominal
A6: B · Realizado no período auditado | B6: 34.15 | C6: =B6*2.4374 -> 83.23721 | D6: =1600*0.2/C6 -> 3.8444345 | E6: o que a conta entregou de fato
A7: C · Teto econômico (recomendado) | B7: 43.85 | C7: =B7*2.4374 -> 106.87999 | D7: =1600*0.2/C7 -> 2.9940123 | E7: mantém LTV/CAC ≥ 3× na margem pessimista
A8: D · Limite absoluto | B8: 60 | C8: =B8*2.4374 -> 146.244 | D8: =1600*0.2/C8 -> 2.188124 | E8: LTV/CAC cai abaixo de 2,5× — não ultrapassar
A10: PREMISSAS
A11: LTV (receita por cliente) | B11: R$ 1.600 | C11: informado pelo cliente em 21/08/2026
A12: Compras por cliente | B12: 8 a 10 | C12: informado pelo cliente
A13: Ticket médio real | B13: R$ 180,00 | C13: informado pelo cliente
A14: Razão CPA incremental ÷ atribuído | B14: 2,44× | C14: medido: janela 07–12/08, lift de 2,12 pedidos/dia
A15: Margem de contribuição | B15: NÃO INFORMADA | C15: cenários usam 20% como pior caso

Sheet Gaps de Tracking
A1: GAPS DE TRACKING — o que impede preencher a planilha por completo
A2: Dois dos quatro degraus do funil do Indicador Base não existem no pixel da Civilitá.
A4: ITEM | B4: SITUAÇÃO | C4: IMPACTO NA PLANILHA | D4: AÇÃO
A5: Evento InitiateCheckout | B5: Não existe no dataset | C5: A linha 'Initiate × Purchase' fica sem taxa. O degrau ATC→IC→Purchase colapsa em ATC→Purchase | D5: Implementar no site — P0
A6: Evento ViewContent | B6: Não existe no dataset | C6: A linha 'View Product × Add to Cart' fica sem taxa | D6: Implementar com content_id — P1
A7: AddToCart × LandingPageView = 117,5% | B7: Defeito confirmado | C7: Taxa acima de 100% é impossível: não se adiciona ao carrinho mais vezes do que se chegou à página | D7: Auditar em que ação o ATC dispara — P0
A8: Purchase value 15% acima do ticket | B8: Meta reporta R$207,18 vs R$180 real | C8: ROAS da conta inflado em ~15% | D8: Verificar se frete entra no value — P1
A9: CAPI (server-side) | B9: Nunca disparou | C9: Cobertura só por navegador; perde iOS e bloqueadores | D9: Implementar com deduplicação — P1
A10: Event Match Quality | B10: Não acessível pela API | C10: Não dá para avaliar qualidade de correspondência | D10: Consultar no Events Manager
A13: CONSEQUÊNCIA PRÁTICA
A14: O Indicador Base foi preenchido com o funil que existe: Clique → Landing Page View → Add to Cart → Venda.
A15: As duas etapas ausentes foram colapsadas (taxa equivalente a 100%), o que é matematicamente correto mas cega o diagnóstico:
A16: não é possível saber se a perda entre carrinho e venda acontece no carrinho, no checkout ou no pagamento.

Sheet Alavancas
A1: ALAVANCAS DE CPA — o que o Indicador Base revela
A2: Os custos unitários da conta cabem com folga na meta de CPA. O que trava não é o preço do clique — são as taxas de conversão.
A4: PONTO DE PARTIDA (medido)
A5: CPC real (link) | B5: =Dados!B22 -> 1.7967326
A6: Cliques por venda | B6: =Dados!B33 -> 19.009174
A7: CPA atribuído | B7: =Dados!B25 -> 34.154404
A8: Connect Rate | B8: =Dados!B29 -> 0.36920849
A9: ATC → Purchase | B9: =Dados!B31 -> 0.12124583
A11: ALAVANCA 1 — CONNECT RATE (corrigir o vazamento clique → página)
A12: CONNECT RATE | B12: CLIQUES POR VENDA | C12: CPA PROJETADO | D12: VARIAÇÃO | E12: SITUAÇÃO
A13: 0.369208 | B13: =(1/$B$9)/1.1751633986928105/A13 -> 19.009174 | C13: =B13*$B$5 -> 34.154404 | D13: =C13/$C$13-1 -> 0 | E13: ◄ situação atual
A14: 0.45 | B14: =(1/$B$9)/1.1751633986928105/A14 -> 15.59633 | C14: =B14*$B$5 -> 28.022435 | D14: =C14/$C$13-1 -> -0.17953668 | E14: meta mínima
A15: 0.55 | B15: =(1/$B$9)/1.1751633986928105/A15 -> 12.760634 | C15: =B15*$B$5 -> 22.927447 | D15: =C15/$C$13-1 -> -0.32871183
A16: 0.7 | B16: =(1/$B$9)/1.1751633986928105/A16 -> 10.026212 | C16: =B16*$B$5 -> 18.014423 | D16: =C16/$C$13-1 -> -0.47255929 | E16: ◄ meta do plano
A17: 0.85 | B17: =(1/$B$9)/1.1751633986928105/A17 -> 8.2568807 | C17: =B17*$B$5 -> 14.835407 | D17: =C17/$C$13-1 -> -0.56563707 | E17: excelente
A19: ALAVANCA 2 — ATC → PURCHASE (oferta e checkout)
A20: ATC → PURCHASE | B20: CLIQUES POR VENDA | C20: CPA PROJETADO | D20: VARIAÇÃO | E20: SITUAÇÃO
A21: 0.121246 | B21: =(1/A21)/1.1751633986928105/$B$8 -> 19.009174 | C21: =B21*$B$5 -> 34.154404 | D21: =C21/$C$21-1 -> 0 | E21: ◄ situação atual
A22: 0.15 | B22: =(1/A22)/1.1751633986928105/$B$8 -> 15.365221 | C22: =B22*$B$5 -> 27.607193 | D22: =C22/$C$21-1 -> -0.19169448
A23: 0.2 | B23: =(1/A23)/1.1751633986928105/$B$8 -> 11.523915 | C23: =B23*$B$5 -> 20.705395 | D23: =C23/$C$21-1 -> -0.39377086 | E23: ◄ meta do plano
A24: 0.25 | B24: =(1/A24)/1.1751633986928105/$B$8 -> 9.2191324 | C24: =B24*$B$5 -> 16.564316 | D24: =C24/$C$21-1 -> -0.51501669
A26: COMBINADO — Connect Rate 70% + ATC→Purchase 20%
A27: Cliques por venda | B27: =(1/0.20)/1.1751633986928105/0.70 -> 6.0781821
A28: CPA projetado | B28: =B27*$B$5 -> 10.920868
A29: Variação vs hoje | B29: =B28/$C$13-1 -> -0.68025007
A31: O QUE ISSO SIGNIFICA PARA A META DE 700 MARMITAS
A32: CENÁRIO | B32: CPA | C32: VENDAS/MÊS A R$7.950
A33: Hoje | B33: =C13 -> 34.154404 | C33: =7950/B33 -> 232.76647
A34: Só corrigindo Connect Rate | B34: =C16 -> 18.014423 | C34: =7950/B34 -> 441.31306
A35: Connect Rate + oferta | B35: =B28 -> 10.920868 | C35: =7950/B35 -> 727.96411
A37: ⚠ RESSALVA METODOLÓGICA
A38: Esta projeção assume que os cliques hoje perdidos antes da página converteriam na mesma taxa dos que chegam.
A39: Parte deles pode ser clique acidental, de menor intenção — nesse caso o ganho real fica abaixo do projetado.
A40: Trate os números como ORDEM DE GRANDEZA da oportunidade, não como promessa. O teste é corrigir a página e medir.
